ghost_speed_check/__init__.py
ghost_speed_check/__main__.py
ghost_speed_check-0.1.dist-info/METADATA
ghost_speed_check-0.1.dist-info/WHEEL
ghost_speed_check-0.1.dist-info/top_level.txt
ghost_speed_check-0.1.dist-info/RECORD
